greening/__init__.py
greening/cli.py
greening/greening_config.py
greening/helpers.py
greening/commands/__init__.py
greening/commands/help.py
greening/commands/init.py
greening/commands/new.py
greening/templates/python-package-template/{{cookiecutter.project_slug}}/.gitignore
greening/templates/python-package-template/{{cookiecutter.project_slug}}/.readthedocs.yaml
greening/templates/python-package-template/{{cookiecutter.project_slug}}/LICENSE
greening/templates/python-package-template/{{cookiecutter.project_slug}}/README.md
greening/templates/python-package-template/{{cookiecutter.project_slug}}/__init__.py
greening/templates/python-package-template/{{cookiecutter.project_slug}}/pyproject.toml
greening/templates/python-package-template/{{cookiecutter.project_slug}}/requirements.txt
greening/templates/python-package-template/{{cookiecutter.project_slug}}/.github/CODE_OF_CONDUCT.md
greening/templates/python-package-template/{{cookiecutter.project_slug}}/.github/CONTRIBUTING.md
greening/templates/python-package-template/{{cookiecutter.project_slug}}/.github/PULL_REQUEST_TEMPLATE.md
greening/templates/python-package-template/{{cookiecutter.project_slug}}/.github/ISSUE_TEMPLATE/bug_report.md
greening/templates/python-package-template/{{cookiecutter.project_slug}}/.github/ISSUE_TEMPLATE/feature_request.md
greening/templates/python-package-template/{{cookiecutter.project_slug}}/.github/workflows/pylint.yml
greening/templates/python-package-template/{{cookiecutter.project_slug}}/.github/workflows/pypi.yml
greening/templates/python-package-template/{{cookiecutter.project_slug}}/.github/workflows/pytest.yml
greening/templates/python-package-template/{{cookiecutter.project_slug}}/docs/Makefile
greening/templates/python-package-template/{{cookiecutter.project_slug}}/docs/make.bat
greening/templates/python-package-template/{{cookiecutter.project_slug}}/docs/source/conf.py
greening/templates/python-package-template/{{cookiecutter.project_slug}}/docs/source/index.rst
greening-0.5.2.dist-info/licenses/LICENSE
greening-0.5.2.dist-info/METADATA
greening-0.5.2.dist-info/WHEEL
greening-0.5.2.dist-info/entry_points.txt
greening-0.5.2.dist-info/top_level.txt
greening-0.5.2.dist-info/RECORD
