Metadata-Version: 2.4
Name: greening
Version: 0.5.2
Summary: A creative dev automation engine for launching, documenting, and publishing projects
Author-email: Christopher Greening <chris@christophergreening.com>
License: MIT
Requires-Python: >=3.7
License-File: LICENSE
Requires-Dist: cookiecutter
Requires-Dist: requests
Requires-Dist: importlib_resources
Dynamic: license-file
